{
  "source": "Polymarket Gamma API",
  "sourceUrl": "https://gamma-api.polymarket.com",
  "generatedAt": "2026-07-02T10:02:23.540Z",
  "matches": [
    {
      "matchId": "worldcup26-84",
      "matchedBy": "teams",
      "kickoffUtc": "2026-07-02T19:00:00.000Z",
      "homeAlt": "Spain",
      "awayAlt": "Austria",
      "homeCode": "ESP",
      "awayCode": "AUT",
      "wdl": {
        "homeWin": 0.7434620174346201,
        "draw": 0.17808219178082194,
        "awayWin": 0.07845579078455792,
        "raw": {
          "homeWin": 0.74625,
          "draw": 0.17875,
          "awayWin": 0.07875
        },
        "marketIds": {
          "awayWin": "2718915",
          "homeWin": "2718913",
          "draw": "2718914"
        },
        "eventSlug": "fifwc-esp-aut-2026-07-02",
        "updatedAt": "2026-07-02T10:00:28.044163Z"
      },
      "exactScore": {
        "scores": [
          {
            "home": 0,
            "away": 0,
            "probability": 0.044798407167745156,
            "rawProbability": 0.045,
            "marketSlug": "fifwc-esp-aut-2026-07-02-exact-score-0-0"
          },
          {
            "home": 0,
            "away": 1,
            "probability": 0.026879044300647095,
            "rawProbability": 0.027,
            "marketSlug": "fifwc-esp-aut-2026-07-02-exact-score-0-1"
          },
          {
            "home": 1,
            "away": 0,
            "probability": 0.12444001991040322,
            "rawProbability": 0.125,
            "marketSlug": "fifwc-esp-aut-2026-07-02-exact-score-1-0"
          },
          {
            "home": 0,
            "away": 2,
            "probability": 0.009457441513190645,
            "rawProbability": 0.0095,
            "marketSlug": "fifwc-esp-aut-2026-07-02-exact-score-0-2"
          },
          {
            "home": 1,
            "away": 1,
            "probability": 0.0846192135390742,
            "rawProbability": 0.085,
            "marketSlug": "fifwc-esp-aut-2026-07-02-exact-score-1-1"
          },
          {
            "home": 2,
            "away": 0,
            "probability": 0.14435042309606771,
            "rawProbability": 0.145,
            "marketSlug": "fifwc-esp-aut-2026-07-02-exact-score-2-0"
          },
          {
            "home": 0,
            "away": 3,
            "probability": 0.0024888003982080644,
            "rawProbability": 0.0025,
            "marketSlug": "fifwc-esp-aut-2026-07-02-exact-score-0-3"
          },
          {
            "home": 1,
            "away": 2,
            "probability": 0.023394723743155807,
            "rawProbability": 0.0235,
            "marketSlug": "fifwc-esp-aut-2026-07-02-exact-score-1-2"
          },
          {
            "home": 2,
            "away": 1,
            "probability": 0.1045296167247387,
            "rawProbability": 0.105,
            "marketSlug": "fifwc-esp-aut-2026-07-02-exact-score-2-1"
          },
          {
            "home": 3,
            "away": 0,
            "probability": 0.1045296167247387,
            "rawProbability": 0.105,
            "marketSlug": "fifwc-esp-aut-2026-07-02-exact-score-3-0"
          },
          {
            "home": 1,
            "away": 3,
            "probability": 0.004479840716774515,
            "rawProbability": 0.0045,
            "marketSlug": "fifwc-esp-aut-2026-07-02-exact-score-1-3"
          },
          {
            "home": 2,
            "away": 2,
            "probability": 0.03583872573419612,
            "rawProbability": 0.036,
            "marketSlug": "fifwc-esp-aut-2026-07-02-exact-score-2-2"
          },
          {
            "home": 3,
            "away": 1,
            "probability": 0.07466401194624193,
            "rawProbability": 0.075,
            "marketSlug": "fifwc-esp-aut-2026-07-02-exact-score-3-1"
          },
          {
            "home": 2,
            "away": 3,
            "probability": 0.0064708810353409675,
            "rawProbability": 0.0065,
            "marketSlug": "fifwc-esp-aut-2026-07-02-exact-score-2-3"
          },
          {
            "home": 3,
            "away": 2,
            "probability": 0.027376804380288708,
            "rawProbability": 0.0275,
            "marketSlug": "fifwc-esp-aut-2026-07-02-exact-score-3-2"
          },
          {
            "home": 3,
            "away": 3,
            "probability": 0.007466401194624193,
            "rawProbability": 0.0075,
            "marketSlug": "fifwc-esp-aut-2026-07-02-exact-score-3-3"
          }
        ],
        "otherProbability": 0.1742160278745645,
        "rawTotal": 1.0044999999999997,
        "eventSlug": "fifwc-esp-aut-2026-07-02-exact-score",
        "updatedAt": "2026-07-02T09:58:47.616215Z"
      }
    },
    {
      "matchId": "worldcup26-83",
      "matchedBy": "teams",
      "kickoffUtc": "2026-07-02T23:00:00.000Z",
      "homeAlt": "Portugal",
      "awayAlt": "Croatia",
      "homeCode": "PRT",
      "awayCode": "HRV",
      "wdl": {
        "homeWin": 0.5673671199011124,
        "draw": 0.2583436341161928,
        "awayWin": 0.17428924598269468,
        "raw": {
          "homeWin": 0.57375,
          "draw": 0.26125,
          "awayWin": 0.17625
        },
        "marketIds": {
          "draw": "2718920",
          "homeWin": "2718919",
          "awayWin": "2718922"
        },
        "eventSlug": "fifwc-prt-hrv-2026-07-02",
        "updatedAt": "2026-07-02T10:00:16.791481Z"
      },
      "exactScore": {
        "scores": [
          {
            "home": 0,
            "away": 0,
            "probability": 0.06493506493506494,
            "rawProbability": 0.065,
            "marketSlug": "fifwc-prt-hrv-2026-07-02-exact-score-0-0"
          },
          {
            "home": 0,
            "away": 1,
            "probability": 0.05494505494505495,
            "rawProbability": 0.055,
            "marketSlug": "fifwc-prt-hrv-2026-07-02-exact-score-0-1"
          },
          {
            "home": 1,
            "away": 0,
            "probability": 0.1048951048951049,
            "rawProbability": 0.105,
            "marketSlug": "fifwc-prt-hrv-2026-07-02-exact-score-1-0"
          },
          {
            "home": 0,
            "away": 2,
            "probability": 0.02447552447552448,
            "rawProbability": 0.0245,
            "marketSlug": "fifwc-prt-hrv-2026-07-02-exact-score-0-2"
          },
          {
            "home": 1,
            "away": 1,
            "probability": 0.1248751248751249,
            "rawProbability": 0.125,
            "marketSlug": "fifwc-prt-hrv-2026-07-02-exact-score-1-1"
          },
          {
            "home": 2,
            "away": 0,
            "probability": 0.09490509490509491,
            "rawProbability": 0.095,
            "marketSlug": "fifwc-prt-hrv-2026-07-02-exact-score-2-0"
          },
          {
            "home": 0,
            "away": 3,
            "probability": 0.007492507492507493,
            "rawProbability": 0.0075,
            "marketSlug": "fifwc-prt-hrv-2026-07-02-exact-score-0-3"
          },
          {
            "home": 1,
            "away": 2,
            "probability": 0.05494505494505495,
            "rawProbability": 0.055,
            "marketSlug": "fifwc-prt-hrv-2026-07-02-exact-score-1-2"
          },
          {
            "home": 2,
            "away": 1,
            "probability": 0.1048951048951049,
            "rawProbability": 0.105,
            "marketSlug": "fifwc-prt-hrv-2026-07-02-exact-score-2-1"
          },
          {
            "home": 3,
            "away": 0,
            "probability": 0.05494505494505495,
            "rawProbability": 0.055,
            "marketSlug": "fifwc-prt-hrv-2026-07-02-exact-score-3-0"
          },
          {
            "home": 1,
            "away": 3,
            "probability": 0.016483516483516487,
            "rawProbability": 0.0165,
            "marketSlug": "fifwc-prt-hrv-2026-07-02-exact-score-1-3"
          },
          {
            "home": 2,
            "away": 2,
            "probability": 0.06493506493506494,
            "rawProbability": 0.065,
            "marketSlug": "fifwc-prt-hrv-2026-07-02-exact-score-2-2"
          },
          {
            "home": 3,
            "away": 1,
            "probability": 0.06493506493506494,
            "rawProbability": 0.065,
            "marketSlug": "fifwc-prt-hrv-2026-07-02-exact-score-3-1"
          },
          {
            "home": 2,
            "away": 3,
            "probability": 0.018981018981018984,
            "rawProbability": 0.019,
            "marketSlug": "fifwc-prt-hrv-2026-07-02-exact-score-2-3"
          },
          {
            "home": 3,
            "away": 2,
            "probability": 0.03796203796203797,
            "rawProbability": 0.038,
            "marketSlug": "fifwc-prt-hrv-2026-07-02-exact-score-3-2"
          },
          {
            "home": 3,
            "away": 3,
            "probability": 0.015484515484515486,
            "rawProbability": 0.0155,
            "marketSlug": "fifwc-prt-hrv-2026-07-02-exact-score-3-3"
          }
        ],
        "otherProbability": 0.08991008991008992,
        "rawTotal": 1.001,
        "eventSlug": "fifwc-prt-hrv-2026-07-02-exact-score",
        "updatedAt": "2026-07-02T09:58:47.616215Z"
      }
    },
    {
      "matchId": "worldcup26-85",
      "matchedBy": "teams",
      "kickoffUtc": "2026-07-03T03:00:00.000Z",
      "homeAlt": "Switzerland",
      "awayAlt": "Algeria",
      "homeCode": "CHE",
      "awayCode": "ALG",
      "wdl": {
        "homeWin": 0.4769613947696139,
        "draw": 0.2976338729763387,
        "awayWin": 0.2254047322540473,
        "raw": {
          "homeWin": 0.47875,
          "draw": 0.29875,
          "awayWin": 0.22625
        },
        "marketIds": {
          "awayWin": "2718928",
          "homeWin": "2718925",
          "draw": "2718926"
        },
        "eventSlug": "fifwc-che-alg-2026-07-02",
        "updatedAt": "2026-07-02T10:00:46.829156Z"
      },
      "exactScore": {
        "scores": [
          {
            "home": 3,
            "away": 0,
            "probability": 0.04522613065326633,
            "rawProbability": 0.045,
            "marketSlug": "fifwc-che-alg-2026-07-02-exact-score-3-0"
          },
          {
            "home": 1,
            "away": 3,
            "probability": 0.015075376884422112,
            "rawProbability": 0.015,
            "marketSlug": "fifwc-che-alg-2026-07-02-exact-score-1-3"
          },
          {
            "home": 2,
            "away": 2,
            "probability": 0.05527638190954774,
            "rawProbability": 0.055,
            "marketSlug": "fifwc-che-alg-2026-07-02-exact-score-2-2"
          },
          {
            "home": 3,
            "away": 1,
            "probability": 0.04522613065326633,
            "rawProbability": 0.045,
            "marketSlug": "fifwc-che-alg-2026-07-02-exact-score-3-1"
          },
          {
            "home": 2,
            "away": 3,
            "probability": 0.0135678391959799,
            "rawProbability": 0.0135,
            "marketSlug": "fifwc-che-alg-2026-07-02-exact-score-2-3"
          },
          {
            "home": 3,
            "away": 2,
            "probability": 0.02562814070351759,
            "rawProbability": 0.0255,
            "marketSlug": "fifwc-che-alg-2026-07-02-exact-score-3-2"
          },
          {
            "home": 3,
            "away": 3,
            "probability": 0.010552763819095479,
            "rawProbability": 0.0105,
            "marketSlug": "fifwc-che-alg-2026-07-02-exact-score-3-3"
          },
          {
            "home": 0,
            "away": 0,
            "probability": 0.09547738693467338,
            "rawProbability": 0.095,
            "marketSlug": "fifwc-che-alg-2026-07-02-exact-score-0-0"
          },
          {
            "home": 0,
            "away": 1,
            "probability": 0.07537688442211056,
            "rawProbability": 0.075,
            "marketSlug": "fifwc-che-alg-2026-07-02-exact-score-0-1"
          },
          {
            "home": 1,
            "away": 0,
            "probability": 0.1256281407035176,
            "rawProbability": 0.125,
            "marketSlug": "fifwc-che-alg-2026-07-02-exact-score-1-0"
          },
          {
            "home": 0,
            "away": 2,
            "probability": 0.032160804020100506,
            "rawProbability": 0.032,
            "marketSlug": "fifwc-che-alg-2026-07-02-exact-score-0-2"
          },
          {
            "home": 1,
            "away": 1,
            "probability": 0.14572864321608042,
            "rawProbability": 0.145,
            "marketSlug": "fifwc-che-alg-2026-07-02-exact-score-1-1"
          },
          {
            "home": 2,
            "away": 0,
            "probability": 0.09547738693467338,
            "rawProbability": 0.095,
            "marketSlug": "fifwc-che-alg-2026-07-02-exact-score-2-0"
          },
          {
            "home": 0,
            "away": 3,
            "probability": 0.008542713567839198,
            "rawProbability": 0.0085,
            "marketSlug": "fifwc-che-alg-2026-07-02-exact-score-0-3"
          },
          {
            "home": 1,
            "away": 2,
            "probability": 0.06532663316582915,
            "rawProbability": 0.065,
            "marketSlug": "fifwc-che-alg-2026-07-02-exact-score-1-2"
          },
          {
            "home": 2,
            "away": 1,
            "probability": 0.09547738693467338,
            "rawProbability": 0.095,
            "marketSlug": "fifwc-che-alg-2026-07-02-exact-score-2-1"
          }
        ],
        "otherProbability": 0.050251256281407045,
        "rawTotal": 0.9949999999999999,
        "eventSlug": "fifwc-che-alg-2026-07-02-exact-score",
        "updatedAt": "2026-07-02T10:00:45.932373Z"
      }
    },
    {
      "matchId": "worldcup26-88",
      "matchedBy": "teams",
      "kickoffUtc": "2026-07-03T18:00:00.000Z",
      "homeAlt": "Australia",
      "awayAlt": "Egypt",
      "homeCode": "AUS",
      "awayCode": "EGY",
      "wdl": {
        "homeWin": 0.2835820895522388,
        "draw": 0.33333333333333337,
        "awayWin": 0.3830845771144279,
        "raw": {
          "homeWin": 0.285,
          "draw": 0.335,
          "awayWin": 0.385
        },
        "marketIds": {
          "homeWin": "2707653",
          "draw": "2707655",
          "awayWin": "2707656"
        },
        "eventSlug": "fifwc-aus-egy-2026-07-03",
        "updatedAt": "2026-07-02T10:00:36.949423Z"
      },
      "exactScore": {
        "scores": [
          {
            "home": 0,
            "away": 0,
            "probability": 0.14399205561072495,
            "rawProbability": 0.145,
            "marketSlug": "fifwc-aus-egy-2026-07-03-exact-score-0-0"
          },
          {
            "home": 0,
            "away": 1,
            "probability": 0.14399205561072495,
            "rawProbability": 0.145,
            "marketSlug": "fifwc-aus-egy-2026-07-03-exact-score-0-1"
          },
          {
            "home": 1,
            "away": 0,
            "probability": 0.11420059582919567,
            "rawProbability": 0.115,
            "marketSlug": "fifwc-aus-egy-2026-07-03-exact-score-1-0"
          },
          {
            "home": 0,
            "away": 2,
            "probability": 0.07447864945382326,
            "rawProbability": 0.075,
            "marketSlug": "fifwc-aus-egy-2026-07-03-exact-score-0-2"
          },
          {
            "home": 1,
            "away": 1,
            "probability": 0.14399205561072495,
            "rawProbability": 0.145,
            "marketSlug": "fifwc-aus-egy-2026-07-03-exact-score-1-1"
          },
          {
            "home": 2,
            "away": 0,
            "probability": 0.04816285998013904,
            "rawProbability": 0.0485,
            "marketSlug": "fifwc-aus-egy-2026-07-03-exact-score-2-0"
          },
          {
            "home": 0,
            "away": 3,
            "probability": 0.0243296921549156,
            "rawProbability": 0.0245,
            "marketSlug": "fifwc-aus-egy-2026-07-03-exact-score-0-3"
          },
          {
            "home": 1,
            "away": 2,
            "probability": 0.07944389275074482,
            "rawProbability": 0.08,
            "marketSlug": "fifwc-aus-egy-2026-07-03-exact-score-1-2"
          },
          {
            "home": 2,
            "away": 1,
            "probability": 0.06454816285998016,
            "rawProbability": 0.065,
            "marketSlug": "fifwc-aus-egy-2026-07-03-exact-score-2-1"
          },
          {
            "home": 3,
            "away": 0,
            "probability": 0.012413108242303877,
            "rawProbability": 0.0125,
            "marketSlug": "fifwc-aus-egy-2026-07-03-exact-score-3-0"
          },
          {
            "home": 1,
            "away": 3,
            "probability": 0.02730883813306853,
            "rawProbability": 0.0275,
            "marketSlug": "fifwc-aus-egy-2026-07-03-exact-score-1-3"
          },
          {
            "home": 2,
            "away": 2,
            "probability": 0.0441906653426018,
            "rawProbability": 0.0445,
            "marketSlug": "fifwc-aus-egy-2026-07-03-exact-score-2-2"
          },
          {
            "home": 3,
            "away": 1,
            "probability": 0.015392254220456807,
            "rawProbability": 0.0155,
            "marketSlug": "fifwc-aus-egy-2026-07-03-exact-score-3-1"
          },
          {
            "home": 2,
            "away": 3,
            "probability": 0.016385302879841118,
            "rawProbability": 0.0165,
            "marketSlug": "fifwc-aus-egy-2026-07-03-exact-score-2-3"
          },
          {
            "home": 3,
            "away": 2,
            "probability": 0.013406156901688187,
            "rawProbability": 0.0135,
            "marketSlug": "fifwc-aus-egy-2026-07-03-exact-score-3-2"
          },
          {
            "home": 3,
            "away": 3,
            "probability": 0.006454816285998016,
            "rawProbability": 0.0065,
            "marketSlug": "fifwc-aus-egy-2026-07-03-exact-score-3-3"
          }
        ],
        "otherProbability": 0.02730883813306853,
        "rawTotal": 1.0069999999999997,
        "eventSlug": "fifwc-aus-egy-2026-07-03-exact-score",
        "updatedAt": "2026-07-02T09:58:47.616215Z"
      }
    },
    {
      "matchId": "worldcup26-86",
      "matchedBy": "teams",
      "kickoffUtc": "2026-07-03T22:00:00.000Z",
      "homeAlt": "Argentina",
      "awayAlt": "Cabo Verde",
      "homeCode": "ARG",
      "awayCode": "CVI",
      "wdl": {
        "homeWin": 0.8420528151469855,
        "draw": 0.114598903836572,
        "awayWin": 0.04334828101644245,
        "raw": {
          "homeWin": 0.845,
          "draw": 0.115,
          "awayWin": 0.0435
        },
        "marketIds": {
          "homeWin": "2707658",
          "draw": "2707659",
          "awayWin": "2707660"
        },
        "eventSlug": "fifwc-arg-cvi-2026-07-03",
        "updatedAt": "2026-07-02T10:00:32.058675Z"
      },
      "exactScore": {
        "scores": [
          {
            "home": 0,
            "away": 0,
            "probability": 0.0474095796676442,
            "rawProbability": 0.0485,
            "marketSlug": "fifwc-arg-cvi-2026-07-03-exact-score-0-0"
          },
          {
            "home": 0,
            "away": 1,
            "probability": 0.020527859237536663,
            "rawProbability": 0.021,
            "marketSlug": "fifwc-arg-cvi-2026-07-03-exact-score-0-1"
          },
          {
            "home": 1,
            "away": 0,
            "probability": 0.13196480938416427,
            "rawProbability": 0.135,
            "marketSlug": "fifwc-arg-cvi-2026-07-03-exact-score-1-0"
          },
          {
            "home": 0,
            "away": 2,
            "probability": 0.004398826979472142,
            "rawProbability": 0.0045,
            "marketSlug": "fifwc-arg-cvi-2026-07-03-exact-score-0-2"
          },
          {
            "home": 1,
            "away": 1,
            "probability": 0.05131964809384166,
            "rawProbability": 0.0525,
            "marketSlug": "fifwc-arg-cvi-2026-07-03-exact-score-1-1"
          },
          {
            "home": 2,
            "away": 0,
            "probability": 0.17106549364613885,
            "rawProbability": 0.175,
            "marketSlug": "fifwc-arg-cvi-2026-07-03-exact-score-2-0"
          },
          {
            "home": 0,
            "away": 3,
            "probability": 0.0009775171065493648,
            "rawProbability": 0.001,
            "marketSlug": "fifwc-arg-cvi-2026-07-03-exact-score-0-3"
          },
          {
            "home": 1,
            "away": 2,
            "probability": 0.013196480938416426,
            "rawProbability": 0.0135,
            "marketSlug": "fifwc-arg-cvi-2026-07-03-exact-score-1-2"
          },
          {
            "home": 2,
            "away": 1,
            "probability": 0.07331378299120236,
            "rawProbability": 0.075,
            "marketSlug": "fifwc-arg-cvi-2026-07-03-exact-score-2-1"
          },
          {
            "home": 3,
            "away": 0,
            "probability": 0.13196480938416427,
            "rawProbability": 0.135,
            "marketSlug": "fifwc-arg-cvi-2026-07-03-exact-score-3-0"
          },
          {
            "home": 1,
            "away": 3,
            "probability": 0.0014662756598240474,
            "rawProbability": 0.0015,
            "marketSlug": "fifwc-arg-cvi-2026-07-03-exact-score-1-3"
          },
          {
            "home": 2,
            "away": 2,
            "probability": 0.016129032258064523,
            "rawProbability": 0.0165,
            "marketSlug": "fifwc-arg-cvi-2026-07-03-exact-score-2-2"
          },
          {
            "home": 3,
            "away": 1,
            "probability": 0.06598240469208214,
            "rawProbability": 0.0675,
            "marketSlug": "fifwc-arg-cvi-2026-07-03-exact-score-3-1"
          },
          {
            "home": 2,
            "away": 3,
            "probability": 0.0034213098729227774,
            "rawProbability": 0.0035,
            "marketSlug": "fifwc-arg-cvi-2026-07-03-exact-score-2-3"
          },
          {
            "home": 3,
            "away": 2,
            "probability": 0.013196480938416426,
            "rawProbability": 0.0135,
            "marketSlug": "fifwc-arg-cvi-2026-07-03-exact-score-3-2"
          },
          {
            "home": 3,
            "away": 3,
            "probability": 0.004398826979472142,
            "rawProbability": 0.0045,
            "marketSlug": "fifwc-arg-cvi-2026-07-03-exact-score-3-3"
          }
        ],
        "otherProbability": 0.24926686217008806,
        "rawTotal": 1.0229999999999997,
        "eventSlug": "fifwc-arg-cvi-2026-07-03-exact-score",
        "updatedAt": "2026-07-02T10:00:45.932373Z"
      }
    },
    {
      "matchId": "worldcup26-87",
      "matchedBy": "teams",
      "kickoffUtc": "2026-07-04T01:30:00.000Z",
      "homeAlt": "Colombia",
      "awayAlt": "Ghana",
      "homeCode": "COL",
      "awayCode": "GHA",
      "wdl": {
        "homeWin": 0.6354679802955664,
        "draw": 0.24137931034482754,
        "awayWin": 0.1231527093596059,
        "raw": {
          "homeWin": 0.645,
          "draw": 0.245,
          "awayWin": 0.125
        },
        "marketIds": {
          "homeWin": "2718931",
          "draw": "2718932",
          "awayWin": "2718933"
        },
        "eventSlug": "fifwc-col-gha-2026-07-03",
        "updatedAt": "2026-07-02T10:00:08.700479Z"
      },
      "exactScore": {
        "scores": [
          {
            "home": 0,
            "away": 0,
            "probability": 0.09387351778656126,
            "rawProbability": 0.095,
            "marketSlug": "fifwc-col-gha-2026-07-03-exact-score-0-0"
          },
          {
            "home": 0,
            "away": 1,
            "probability": 0.05434782608695652,
            "rawProbability": 0.055,
            "marketSlug": "fifwc-col-gha-2026-07-03-exact-score-0-1"
          },
          {
            "home": 1,
            "away": 0,
            "probability": 0.15810276679841898,
            "rawProbability": 0.16,
            "marketSlug": "fifwc-col-gha-2026-07-03-exact-score-1-0"
          },
          {
            "home": 0,
            "away": 2,
            "probability": 0.015316205533596838,
            "rawProbability": 0.0155,
            "marketSlug": "fifwc-col-gha-2026-07-03-exact-score-0-2"
          },
          {
            "home": 1,
            "away": 1,
            "probability": 0.10375494071146245,
            "rawProbability": 0.105,
            "marketSlug": "fifwc-col-gha-2026-07-03-exact-score-1-1"
          },
          {
            "home": 2,
            "away": 0,
            "probability": 0.14328063241106717,
            "rawProbability": 0.145,
            "marketSlug": "fifwc-col-gha-2026-07-03-exact-score-2-0"
          },
          {
            "home": 0,
            "away": 3,
            "probability": 0.004446640316205533,
            "rawProbability": 0.0045,
            "marketSlug": "fifwc-col-gha-2026-07-03-exact-score-0-3"
          },
          {
            "home": 1,
            "away": 2,
            "probability": 0.031126482213438736,
            "rawProbability": 0.0315,
            "marketSlug": "fifwc-col-gha-2026-07-03-exact-score-1-2"
          },
          {
            "home": 2,
            "away": 1,
            "probability": 0.09387351778656126,
            "rawProbability": 0.095,
            "marketSlug": "fifwc-col-gha-2026-07-03-exact-score-2-1"
          },
          {
            "home": 3,
            "away": 0,
            "probability": 0.0741106719367589,
            "rawProbability": 0.075,
            "marketSlug": "fifwc-col-gha-2026-07-03-exact-score-3-0"
          },
          {
            "home": 1,
            "away": 3,
            "probability": 0.00691699604743083,
            "rawProbability": 0.007,
            "marketSlug": "fifwc-col-gha-2026-07-03-exact-score-1-3"
          },
          {
            "home": 2,
            "away": 2,
            "probability": 0.031126482213438736,
            "rawProbability": 0.0315,
            "marketSlug": "fifwc-col-gha-2026-07-03-exact-score-2-2"
          },
          {
            "home": 3,
            "away": 1,
            "probability": 0.05434782608695652,
            "rawProbability": 0.055,
            "marketSlug": "fifwc-col-gha-2026-07-03-exact-score-3-1"
          },
          {
            "home": 2,
            "away": 3,
            "probability": 0.007905138339920948,
            "rawProbability": 0.008,
            "marketSlug": "fifwc-col-gha-2026-07-03-exact-score-2-3"
          },
          {
            "home": 3,
            "away": 2,
            "probability": 0.022727272727272728,
            "rawProbability": 0.023,
            "marketSlug": "fifwc-col-gha-2026-07-03-exact-score-3-2"
          },
          {
            "home": 3,
            "away": 3,
            "probability": 0.005928853754940712,
            "rawProbability": 0.006,
            "marketSlug": "fifwc-col-gha-2026-07-03-exact-score-3-3"
          }
        ],
        "otherProbability": 0.09881422924901186,
        "rawTotal": 1.012,
        "eventSlug": "fifwc-col-gha-2026-07-03-exact-score",
        "updatedAt": "2026-07-02T09:58:47.616215Z"
      }
    },
    {
      "matchId": "worldcup26-90",
      "matchedBy": "teams",
      "kickoffUtc": "2026-07-04T17:00:00.000Z",
      "homeAlt": "Canada",
      "awayAlt": "Morocco",
      "homeCode": "CAN",
      "awayCode": "MAR",
      "wdl": {
        "homeWin": 0.18407960199004972,
        "draw": 0.2736318407960199,
        "awayWin": 0.5422885572139303,
        "raw": {
          "homeWin": 0.185,
          "draw": 0.275,
          "awayWin": 0.545
        },
        "marketIds": {
          "draw": "2740919",
          "awayWin": "2740921",
          "homeWin": "2740917"
        },
        "eventSlug": "fifwc-can-mar-2026-07-04",
        "updatedAt": "2026-07-02T10:00:45.932373Z"
      },
      "exactScore": {
        "scores": [
          {
            "home": 0,
            "away": 0,
            "probability": 0.09354536950420955,
            "rawProbability": 0.1,
            "marketSlug": "fifwc-can-mar-2026-07-04-exact-score-0-0"
          },
          {
            "home": 0,
            "away": 1,
            "probability": 0.1449953227315248,
            "rawProbability": 0.155,
            "marketSlug": "fifwc-can-mar-2026-07-04-exact-score-0-1"
          },
          {
            "home": 1,
            "away": 0,
            "probability": 0.07015902712815715,
            "rawProbability": 0.075,
            "marketSlug": "fifwc-can-mar-2026-07-04-exact-score-1-0"
          },
          {
            "home": 0,
            "away": 2,
            "probability": 0.1028999064546305,
            "rawProbability": 0.11,
            "marketSlug": "fifwc-can-mar-2026-07-04-exact-score-0-2"
          },
          {
            "home": 1,
            "away": 1,
            "probability": 0.1262862488306829,
            "rawProbability": 0.135,
            "marketSlug": "fifwc-can-mar-2026-07-04-exact-score-1-1"
          },
          {
            "home": 2,
            "away": 0,
            "probability": 0.028999064546304958,
            "rawProbability": 0.031,
            "marketSlug": "fifwc-can-mar-2026-07-04-exact-score-2-0"
          },
          {
            "home": 0,
            "away": 3,
            "probability": 0.05519176800748363,
            "rawProbability": 0.059,
            "marketSlug": "fifwc-can-mar-2026-07-04-exact-score-0-3"
          },
          {
            "home": 1,
            "away": 2,
            "probability": 0.09822263797942002,
            "rawProbability": 0.105,
            "marketSlug": "fifwc-can-mar-2026-07-04-exact-score-1-2"
          },
          {
            "home": 2,
            "away": 1,
            "probability": 0.046772684752104776,
            "rawProbability": 0.05,
            "marketSlug": "fifwc-can-mar-2026-07-04-exact-score-2-1"
          },
          {
            "home": 3,
            "away": 0,
            "probability": 0.008419083255378858,
            "rawProbability": 0.009,
            "marketSlug": "fifwc-can-mar-2026-07-04-exact-score-3-0"
          },
          {
            "home": 1,
            "away": 3,
            "probability": 0.046772684752104776,
            "rawProbability": 0.05,
            "marketSlug": "fifwc-can-mar-2026-07-04-exact-score-1-3"
          },
          {
            "home": 2,
            "away": 2,
            "probability": 0.046772684752104776,
            "rawProbability": 0.05,
            "marketSlug": "fifwc-can-mar-2026-07-04-exact-score-2-2"
          },
          {
            "home": 3,
            "away": 1,
            "probability": 0.011225444340505146,
            "rawProbability": 0.012,
            "marketSlug": "fifwc-can-mar-2026-07-04-exact-score-3-1"
          },
          {
            "home": 2,
            "away": 3,
            "probability": 0.01917680074836296,
            "rawProbability": 0.0205,
            "marketSlug": "fifwc-can-mar-2026-07-04-exact-score-2-3"
          },
          {
            "home": 3,
            "away": 2,
            "probability": 0.010757717492984098,
            "rawProbability": 0.0115,
            "marketSlug": "fifwc-can-mar-2026-07-04-exact-score-3-2"
          },
          {
            "home": 3,
            "away": 3,
            "probability": 0.007951356407857811,
            "rawProbability": 0.0085,
            "marketSlug": "fifwc-can-mar-2026-07-04-exact-score-3-3"
          }
        ],
        "otherProbability": 0.08185219831618334,
        "rawTotal": 1.069,
        "eventSlug": "fifwc-can-mar-2026-07-04-exact-score",
        "updatedAt": "2026-07-02T09:58:47.616215Z"
      }
    },
    {
      "matchId": "worldcup26-89",
      "matchedBy": "teams",
      "kickoffUtc": "2026-07-04T21:00:00.000Z",
      "homeAlt": "Paraguay",
      "awayAlt": "France",
      "homeCode": "PAR",
      "awayCode": "FRA",
      "wdl": {
        "homeWin": 0.04477611940298508,
        "draw": 0.12437810945273634,
        "awayWin": 0.8308457711442787,
        "raw": {
          "homeWin": 0.045,
          "draw": 0.125,
          "awayWin": 0.835
        },
        "marketIds": {
          "draw": "2754627",
          "homeWin": "2754625",
          "awayWin": "2754628"
        },
        "eventSlug": "fifwc-par-fra-2026-07-04",
        "updatedAt": "2026-07-02T10:00:24.897717Z"
      },
      "exactScore": {
        "scores": [
          {
            "home": 2,
            "away": 2,
            "probability": 0.02395490840770314,
            "rawProbability": 0.0255,
            "marketSlug": "fifwc-par-fra-2026-07-04-exact-score-2-2"
          },
          {
            "home": 3,
            "away": 1,
            "probability": 0.002818224518553311,
            "rawProbability": 0.003,
            "marketSlug": "fifwc-par-fra-2026-07-04-exact-score-3-1"
          },
          {
            "home": 2,
            "away": 3,
            "probability": 0.020666979802724278,
            "rawProbability": 0.022,
            "marketSlug": "fifwc-par-fra-2026-07-04-exact-score-2-3"
          },
          {
            "home": 3,
            "away": 2,
            "probability": 0.0037576326914044145,
            "rawProbability": 0.004,
            "marketSlug": "fifwc-par-fra-2026-07-04-exact-score-3-2"
          },
          {
            "home": 0,
            "away": 0,
            "probability": 0.041333959605448556,
            "rawProbability": 0.044,
            "marketSlug": "fifwc-par-fra-2026-07-04-exact-score-0-0"
          },
          {
            "home": 0,
            "away": 1,
            "probability": 0.11742602160638795,
            "rawProbability": 0.125,
            "marketSlug": "fifwc-par-fra-2026-07-04-exact-score-0-1"
          },
          {
            "home": 2,
            "away": 0,
            "probability": 0.004697040864255518,
            "rawProbability": 0.005,
            "marketSlug": "fifwc-par-fra-2026-07-04-exact-score-2-0"
          },
          {
            "home": 3,
            "away": 3,
            "probability": 0.0051667449506810695,
            "rawProbability": 0.0055,
            "marketSlug": "fifwc-par-fra-2026-07-04-exact-score-3-3"
          },
          {
            "home": 1,
            "away": 0,
            "probability": 0.018788163457022073,
            "rawProbability": 0.02,
            "marketSlug": "fifwc-par-fra-2026-07-04-exact-score-1-0"
          },
          {
            "home": 0,
            "away": 2,
            "probability": 0.1550023485204321,
            "rawProbability": 0.165,
            "marketSlug": "fifwc-par-fra-2026-07-04-exact-score-0-2"
          },
          {
            "home": 1,
            "away": 1,
            "probability": 0.05777360263034287,
            "rawProbability": 0.0615,
            "marketSlug": "fifwc-par-fra-2026-07-04-exact-score-1-1"
          },
          {
            "home": 0,
            "away": 3,
            "probability": 0.126820103334899,
            "rawProbability": 0.135,
            "marketSlug": "fifwc-par-fra-2026-07-04-exact-score-0-3"
          },
          {
            "home": 1,
            "away": 2,
            "probability": 0.08454673555659932,
            "rawProbability": 0.09,
            "marketSlug": "fifwc-par-fra-2026-07-04-exact-score-1-2"
          },
          {
            "home": 2,
            "away": 1,
            "probability": 0.011272898074213243,
            "rawProbability": 0.012,
            "marketSlug": "fifwc-par-fra-2026-07-04-exact-score-2-1"
          },
          {
            "home": 3,
            "away": 0,
            "probability": 0.0018788163457022073,
            "rawProbability": 0.002,
            "marketSlug": "fifwc-par-fra-2026-07-04-exact-score-3-0"
          },
          {
            "home": 1,
            "away": 3,
            "probability": 0.06575857209957726,
            "rawProbability": 0.07,
            "marketSlug": "fifwc-par-fra-2026-07-04-exact-score-1-3"
          }
        ],
        "otherProbability": 0.2583372475340535,
        "rawTotal": 1.0645000000000002,
        "eventSlug": "fifwc-par-fra-2026-07-04-exact-score",
        "updatedAt": "2026-07-02T09:58:47.616215Z"
      }
    },
    {
      "matchId": "worldcup26-91",
      "matchedBy": "teams",
      "kickoffUtc": "2026-07-05T20:00:00.000Z",
      "homeAlt": "Brazil",
      "awayAlt": "Norway",
      "homeCode": "BRA",
      "awayCode": "NOR",
      "wdl": {
        "homeWin": 0.5175879396984925,
        "draw": 0.2663316582914573,
        "awayWin": 0.21608040201005024,
        "raw": {
          "homeWin": 0.515,
          "draw": 0.265,
          "awayWin": 0.215
        },
        "marketIds": {
          "homeWin": "2754647",
          "draw": "2754649",
          "awayWin": "2754651"
        },
        "eventSlug": "fifwc-bra-nor-2026-07-05",
        "updatedAt": "2026-07-02T09:59:47.623111Z"
      },
      "exactScore": {
        "scores": [
          {
            "home": 0,
            "away": 2,
            "probability": 0.026339691189827426,
            "rawProbability": 0.029,
            "marketSlug": "fifwc-bra-nor-2026-07-05-exact-score-0-2"
          },
          {
            "home": 1,
            "away": 1,
            "probability": 0.12261580381471389,
            "rawProbability": 0.135,
            "marketSlug": "fifwc-bra-nor-2026-07-05-exact-score-1-1"
          },
          {
            "home": 2,
            "away": 3,
            "probability": 0.02406902815622161,
            "rawProbability": 0.0265,
            "marketSlug": "fifwc-bra-nor-2026-07-05-exact-score-2-3"
          },
          {
            "home": 0,
            "away": 0,
            "probability": 0.059037238873751126,
            "rawProbability": 0.065,
            "marketSlug": "fifwc-bra-nor-2026-07-05-exact-score-0-0"
          },
          {
            "home": 0,
            "away": 1,
            "probability": 0.06357856494096276,
            "rawProbability": 0.07,
            "marketSlug": "fifwc-bra-nor-2026-07-05-exact-score-0-1"
          },
          {
            "home": 1,
            "away": 0,
            "probability": 0.09536784741144412,
            "rawProbability": 0.105,
            "marketSlug": "fifwc-bra-nor-2026-07-05-exact-score-1-0"
          },
          {
            "home": 2,
            "away": 0,
            "probability": 0.08628519527702087,
            "rawProbability": 0.095,
            "marketSlug": "fifwc-bra-nor-2026-07-05-exact-score-2-0"
          },
          {
            "home": 0,
            "away": 3,
            "probability": 0.022706630336058128,
            "rawProbability": 0.025,
            "marketSlug": "fifwc-bra-nor-2026-07-05-exact-score-0-3"
          },
          {
            "home": 1,
            "away": 2,
            "probability": 0.059037238873751126,
            "rawProbability": 0.065,
            "marketSlug": "fifwc-bra-nor-2026-07-05-exact-score-1-2"
          },
          {
            "home": 2,
            "away": 1,
            "probability": 0.09536784741144412,
            "rawProbability": 0.105,
            "marketSlug": "fifwc-bra-nor-2026-07-05-exact-score-2-1"
          },
          {
            "home": 3,
            "away": 0,
            "probability": 0.045413260672116255,
            "rawProbability": 0.05,
            "marketSlug": "fifwc-bra-nor-2026-07-05-exact-score-3-0"
          },
          {
            "home": 1,
            "away": 3,
            "probability": 0.032697547683923696,
            "rawProbability": 0.036,
            "marketSlug": "fifwc-bra-nor-2026-07-05-exact-score-1-3"
          },
          {
            "home": 2,
            "away": 2,
            "probability": 0.054495912806539495,
            "rawProbability": 0.06,
            "marketSlug": "fifwc-bra-nor-2026-07-05-exact-score-2-2"
          },
          {
            "home": 3,
            "away": 1,
            "probability": 0.054495912806539495,
            "rawProbability": 0.06,
            "marketSlug": "fifwc-bra-nor-2026-07-05-exact-score-3-1"
          },
          {
            "home": 3,
            "away": 2,
            "probability": 0.040871934604904625,
            "rawProbability": 0.045,
            "marketSlug": "fifwc-bra-nor-2026-07-05-exact-score-3-2"
          },
          {
            "home": 3,
            "away": 3,
            "probability": 0.01771117166212534,
            "rawProbability": 0.0195,
            "marketSlug": "fifwc-bra-nor-2026-07-05-exact-score-3-3"
          }
        ],
        "otherProbability": 0.09990917347865574,
        "rawTotal": 1.1010000000000002,
        "eventSlug": "fifwc-bra-nor-2026-07-05-exact-score",
        "updatedAt": "2026-07-02T10:00:45.932373Z"
      }
    }
  ],
  "unmatchedEvents": [],
  "settledResults": [
    {
      "matchId": "worldcup26-68",
      "kickoffUtc": "2026-06-27T21:00:00.000Z",
      "homeScore": 2,
      "awayScore": 1,
      "eventSlug": "fifwc-hrv-gha-2026-06-27-exact-score",
      "resolvedAt": "2026-06-28T23:31:58.018578Z",
      "resolutionVerified": true
    },
    {
      "matchId": "worldcup26-67",
      "kickoffUtc": "2026-06-27T21:00:00.000Z",
      "homeScore": 0,
      "awayScore": 2,
      "eventSlug": "fifwc-pan-eng-2026-06-27-exact-score",
      "resolvedAt": "2026-06-28T23:30:06.030472Z",
      "resolutionVerified": true
    },
    {
      "matchId": "worldcup26-71",
      "kickoffUtc": "2026-06-27T23:30:00.000Z",
      "homeScore": 0,
      "awayScore": 0,
      "eventSlug": "fifwc-col-prt-2026-06-27-exact-score",
      "resolvedAt": "2026-06-29T01:54:00.471275Z",
      "resolutionVerified": true
    },
    {
      "matchId": "worldcup26-72",
      "kickoffUtc": "2026-06-27T23:30:00.000Z",
      "homeScore": 3,
      "awayScore": 1,
      "eventSlug": "fifwc-cdr-uzb-2026-06-27-exact-score",
      "resolvedAt": "2026-06-29T02:04:09.125497Z",
      "resolutionVerified": true
    },
    {
      "matchId": "worldcup26-69",
      "kickoffUtc": "2026-06-28T02:00:00.000Z",
      "homeScore": 3,
      "awayScore": 3,
      "eventSlug": "fifwc-alg-aut-2026-06-27-exact-score",
      "resolvedAt": "2026-06-29T04:29:59.865062Z",
      "resolutionVerified": true
    },
    {
      "matchId": "worldcup26-70",
      "kickoffUtc": "2026-06-28T02:00:00.000Z",
      "homeScore": 1,
      "awayScore": 3,
      "eventSlug": "fifwc-jor-arg-2026-06-27-exact-score",
      "resolvedAt": "2026-06-29T04:18:08.838287Z",
      "resolutionVerified": true
    },
    {
      "matchId": "worldcup26-73",
      "kickoffUtc": "2026-06-28T19:00:00.000Z",
      "homeScore": 0,
      "awayScore": 1,
      "eventSlug": "fifwc-rsa-can-2026-06-28-exact-score",
      "resolvedAt": "2026-06-29T21:47:41.970701Z",
      "resolutionVerified": true
    },
    {
      "matchId": "worldcup26-76",
      "kickoffUtc": "2026-06-29T17:00:00.000Z",
      "homeScore": 2,
      "awayScore": 1,
      "eventSlug": "fifwc-bra-jpn-2026-06-29-exact-score",
      "resolvedAt": "2026-06-30T19:25:55.751229Z",
      "resolutionVerified": true
    },
    {
      "matchId": "worldcup26-74",
      "kickoffUtc": "2026-06-29T20:30:00.000Z",
      "homeScore": 1,
      "awayScore": 1,
      "eventSlug": "fifwc-ger-par-2026-06-29-exact-score",
      "resolvedAt": "2026-06-30T23:47:56.946384Z",
      "resolutionVerified": true
    },
    {
      "matchId": "worldcup26-75",
      "kickoffUtc": "2026-06-30T01:00:00.000Z",
      "homeScore": 1,
      "awayScore": 1,
      "eventSlug": "fifwc-nld-mar-2026-06-29-exact-score",
      "resolvedAt": "2026-07-01T04:15:57.762946Z",
      "resolutionVerified": true
    },
    {
      "matchId": "worldcup26-78",
      "kickoffUtc": "2026-06-30T17:00:00.000Z",
      "homeScore": 1,
      "awayScore": 2,
      "eventSlug": "fifwc-civ-nor-2026-06-30-exact-score",
      "resolvedAt": "2026-07-01T19:33:09.326917Z",
      "resolutionVerified": true
    },
    {
      "matchId": "worldcup26-77",
      "kickoffUtc": "2026-06-30T21:00:00.000Z",
      "homeScore": 3,
      "awayScore": 0,
      "eventSlug": "fifwc-fra-swe-2026-06-30-exact-score",
      "resolvedAt": "2026-07-01T23:23:08.825221Z",
      "resolutionVerified": true
    },
    {
      "matchId": "worldcup26-79",
      "kickoffUtc": "2026-07-01T01:00:00.000Z",
      "homeScore": 2,
      "awayScore": 0,
      "eventSlug": "fifwc-mex-ecu-2026-06-30-exact-score",
      "resolvedAt": "2026-07-02T05:07:11.684388Z",
      "resolutionVerified": true
    },
    {
      "matchId": "worldcup26-80",
      "kickoffUtc": "2026-07-01T16:00:00.000Z",
      "homeScore": 2,
      "awayScore": 1,
      "eventSlug": "fifwc-eng-cdr-2026-07-01-exact-score",
      "resolvedAt": "2026-07-02T10:00:51.906073Z",
      "resolutionVerified": true
    },
    {
      "matchId": "worldcup26-82",
      "kickoffUtc": "2026-07-01T20:00:00.000Z",
      "homeScore": 2,
      "awayScore": 2,
      "eventSlug": "fifwc-bel-sen-2026-07-01-exact-score",
      "resolvedAt": "2026-07-02T10:00:51.906073Z",
      "resolutionVerified": true
    },
    {
      "matchId": "worldcup26-81",
      "kickoffUtc": "2026-07-02T00:00:00.000Z",
      "homeScore": 2,
      "awayScore": 0,
      "eventSlug": "fifwc-usa-bih-2026-07-01-exact-score",
      "resolvedAt": "2026-07-02T10:00:51.906073Z",
      "resolutionVerified": true
    }
  ]
}
